seastream/__init__.py
seastream/registry.py
seastream/stream.py
seastream-0.0.1.dist-info/LICENSE
seastream-0.0.1.dist-info/METADATA
seastream-0.0.1.dist-info/WHEEL
seastream-0.0.1.dist-info/top_level.txt
seastream-0.0.1.dist-info/RECORD
